testlobby/__init__.py
testlobby-0.0.1.dist-info/METADATA
testlobby-0.0.1.dist-info/WHEEL
testlobby-0.0.1.dist-info/RECORD
