Metadata-Version: 2.1
Name: testlobby
Version: 0.0.1
Summary: V2 Fortnite Lobby Bot
Project-URL: Homepage, https://package.lobbybots.xyz
Project-URL: Discord, https://discord.gg/73t72uNYFp
Project-URL: Tutorial, https://youtu.be/HoPHUgkQNYY
Author-email: 2235 <support@lobbybots.xyz>
Classifier: Programming Language :: Python :: 3
Requires-Python: >=3.7
